nose_json
