Metadata-Version: 1.0
Name: nose-json
Version: 0.2.3
Summary: A JSON report plugin for Nose.
Home-page: http://github.com/dcramer/nose-json
Author: David Cramer
Author-email: dcramer@gmail.com
License: Apache License 2.0
Platform: UNKNOWN
Classifier: Intended Audience :: Developers
Classifier: Intended Audience :: System Administrators
Classifier: Operating System :: OS Independent
Classifier: Topic :: Software Development
